{
    "asset": {
        "format": "jpg",
        "id": "01be6bccf5f5549b8ab3f94b9bc4fccb",
        "name": "711250dc2e0f.jpg",
        "path": "file:F:/ArTaxOr/Diptera/711250dc2e0f.jpg",
        "size": {
            "width": 4055,
            "height": 2860
        },
        "state": 2,
        "type": 1
    },
    "regions": [
        {
            "id": "F_zGhQ-BF",
            "type": "RECTANGLE",
            "tags": [
                "Diptera"
            ],
            "boundingBox": {
                "height": 668.1720430107528,
                "width": 659.5313576843556,
                "left": 1000.4755341144038,
                "top": 642.1807795698925
            },
            "points": [
                {
                    "x": 1000.4755341144038,
                    "y": 642.1807795698925
                },
                {
                    "x": 1660.0068917987594,
                    "y": 642.1807795698925
                },
                {
                    "x": 1660.0068917987594,
                    "y": 1310.3528225806454
                },
                {
                    "x": 1000.4755341144038,
                    "y": 1310.3528225806454
                }
            ]
        }
    ],
    "version": "2.1.0"
}