{
    "asset": {
        "format": "jpg",
        "id": "09fc52fbf52fe9a75bb691584556fbdd",
        "name": "51e6c0b86a82.jpg",
        "path": "file:F:/ArTaxOr/Odonata/51e6c0b86a82.jpg",
        "size": {
            "width": 1600,
            "height": 1200
        },
        "state": 2,
        "type": 1
    },
    "regions": [
        {
            "id": "6kE4Kq1Hg",
            "type": "RECTANGLE",
            "tags": [
                "Odonata",
                "_occluded"
            ],
            "boundingBox": {
                "height": 757.471264367816,
                "width": 1501.1494252873563,
                "left": 52.8735632183908,
                "top": 50.574712643678154
            },
            "points": [
                {
                    "x": 52.8735632183908,
                    "y": 50.574712643678154
                },
                {
                    "x": 1554.022988505747,
                    "y": 50.574712643678154
                },
                {
                    "x": 1554.022988505747,
                    "y": 808.0459770114942
                },
                {
                    "x": 52.8735632183908,
                    "y": 808.0459770114942
                }
            ]
        }
    ],
    "version": "2.1.0"
}