{
    "asset": {
        "format": "jpg",
        "id": "1332d2c7a4c81e7539a9caf8b5a45f1b",
        "name": "d02cfb30348d.jpg",
        "path": "file:F:/ArTaxOr/Araneae/d02cfb30348d.jpg",
        "size": {
            "width": 2048,
            "height": 1365
        },
        "state": 2,
        "type": 1
    },
    "regions": [
        {
            "id": "_IAQVymE5",
            "type": "RECTANGLE",
            "tags": [
                "Araneae"
            ],
            "boundingBox": {
                "height": 446.5217391304348,
                "width": 497.16965517241374,
                "left": 754.2289655172414,
                "top": 289.9830163043478
            },
            "points": [
                {
                    "x": 754.2289655172414,
                    "y": 289.9830163043478
                },
                {
                    "x": 1251.398620689655,
                    "y": 289.9830163043478
                },
                {
                    "x": 1251.398620689655,
                    "y": 736.5047554347826
                },
                {
                    "x": 754.2289655172414,
                    "y": 736.5047554347826
                }
            ]
        }
    ],
    "version": "2.1.0"
}