{
    "asset": {
        "format": "jpg",
        "id": "13891b0e520c2381da9efc0adae726e2",
        "name": "32e1d6164a84.jpg",
        "path": "file:F:/ArTaxOr/Coleoptera/32e1d6164a84.jpg",
        "size": {
            "width": 1536,
            "height": 2048
        },
        "state": 2,
        "type": 1
    },
    "regions": [
        {
            "id": "dNRlzwavp",
            "type": "RECTANGLE",
            "tags": [
                "Coleoptera"
            ],
            "boundingBox": {
                "height": 1045.5785440613026,
                "width": 600.2758620689655,
                "left": 474.727969348659,
                "top": 753.2873563218391
            },
            "points": [
                {
                    "x": 474.727969348659,
                    "y": 753.2873563218391
                },
                {
                    "x": 1075.0038314176245,
                    "y": 753.2873563218391
                },
                {
                    "x": 1075.0038314176245,
                    "y": 1798.8659003831417
                },
                {
                    "x": 474.727969348659,
                    "y": 1798.8659003831417
                }
            ]
        }
    ],
    "version": "2.1.0"
}