{
    "asset": {
        "format": "jpg",
        "id": "1964f5fda0a53b189f550533760eb05a",
        "name": "e53156d3dec1.jpg",
        "path": "file:F:/ArTaxOr/Odonata/e53156d3dec1.jpg",
        "size": {
            "width": 1985,
            "height": 1383
        },
        "state": 2,
        "type": 1
    },
    "regions": [
        {
            "id": "CPf4-Fn92",
            "type": "RECTANGLE",
            "tags": [
                "Odonata"
            ],
            "boundingBox": {
                "height": 1086.7967289719625,
                "width": 1516.4839934888769,
                "left": 276.2292288388497,
                "top": 183.10747663551402
            },
            "points": [
                {
                    "x": 276.2292288388497,
                    "y": 183.10747663551402
                },
                {
                    "x": 1792.7132223277265,
                    "y": 183.10747663551402
                },
                {
                    "x": 1792.7132223277265,
                    "y": 1269.9042056074766
                },
                {
                    "x": 276.2292288388497,
                    "y": 1269.9042056074766
                }
            ]
        }
    ],
    "version": "2.1.0"
}