{
    "asset": {
        "format": "jpg",
        "id": "28b58f7a59d8324138b2568a59fcb162",
        "name": "e3aa6716e11e.jpg",
        "path": "file:F:/ArTaxOr/Araneae/e3aa6716e11e.jpg",
        "size": {
            "width": 2048,
            "height": 1274
        },
        "state": 2,
        "type": 1
    },
    "regions": [
        {
            "id": "lM3DifsOo",
            "type": "RECTANGLE",
            "tags": [
                "Araneae"
            ],
            "boundingBox": {
                "height": 795.190687361419,
                "width": 961.8537931034482,
                "left": 560.7282758620689,
                "top": 241.5453506097561
            },
            "points": [
                {
                    "x": 560.7282758620689,
                    "y": 241.5453506097561
                },
                {
                    "x": 1522.5820689655172,
                    "y": 241.5453506097561
                },
                {
                    "x": 1522.5820689655172,
                    "y": 1036.7360379711752
                },
                {
                    "x": 560.7282758620689,
                    "y": 1036.7360379711752
                }
            ]
        }
    ],
    "version": "2.1.0"
}