{
    "asset": {
        "format": "jpg",
        "id": "3068a1bebda0ea9cfdfacd8e4dbd10ae",
        "name": "a61db20b8047.jpg",
        "path": "file:F:/ArTaxOr/Hymenoptera/a61db20b8047.jpg",
        "size": {
            "width": 2048,
            "height": 1365
        },
        "state": 2,
        "type": 1
    },
    "regions": [
        {
            "id": "oG_ZEB4nH",
            "type": "RECTANGLE",
            "tags": [
                "Hymenoptera"
            ],
            "boundingBox": {
                "height": 224.44157187176836,
                "width": 395.20330806340456,
                "left": 505.29565816678155,
                "top": 822.3348629782835
            },
            "points": [
                {
                    "x": 505.29565816678155,
                    "y": 822.3348629782835
                },
                {
                    "x": 900.498966230186,
                    "y": 822.3348629782835
                },
                {
                    "x": 900.498966230186,
                    "y": 1046.7764348500518
                },
                {
                    "x": 505.29565816678155,
                    "y": 1046.7764348500518
                }
            ]
        }
    ],
    "version": "2.1.0"
}