{
    "asset": {
        "format": "jpg",
        "id": "4f172e330ea0978c8551c7a7b06a0a72",
        "name": "ac353d8b8747.jpg",
        "path": "file:F:/ArTaxOr/Odonata/ac353d8b8747.jpg",
        "size": {
            "width": 1515,
            "height": 2048
        },
        "state": 2,
        "type": 1
    },
    "regions": [
        {
            "id": "cjB3Q4VpF",
            "type": "RECTANGLE",
            "tags": [
                "Odonata"
            ],
            "boundingBox": {
                "height": 1580.6604361370717,
                "width": 1054.121052631579,
                "left": 302.8754111842105,
                "top": 301.4579439252336
            },
            "points": [
                {
                    "x": 302.8754111842105,
                    "y": 301.4579439252336
                },
                {
                    "x": 1356.9964638157896,
                    "y": 301.4579439252336
                },
                {
                    "x": 1356.9964638157896,
                    "y": 1882.1183800623053
                },
                {
                    "x": 302.8754111842105,
                    "y": 1882.1183800623053
                }
            ]
        }
    ],
    "version": "2.1.0"
}