{
    "asset": {
        "format": "jpg",
        "id": "563d1d9f5d5a48ac39f20a086ffd73a9",
        "name": "1a6cab41283d.jpg",
        "path": "file:F:/ArTaxOr/Odonata/1a6cab41283d.jpg",
        "size": {
            "width": 2048,
            "height": 1357
        },
        "state": 2,
        "type": 1
    },
    "regions": [
        {
            "id": "QnPRHFhYA",
            "type": "RECTANGLE",
            "tags": [
                "Odonata"
            ],
            "boundingBox": {
                "height": 1051.9927159209158,
                "width": 1023.9999999999999,
                "left": 579.0896551724137,
                "top": 216.59841636316338
            },
            "points": [
                {
                    "x": 579.0896551724137,
                    "y": 216.59841636316338
                },
                {
                    "x": 1603.0896551724136,
                    "y": 216.59841636316338
                },
                {
                    "x": 1603.0896551724136,
                    "y": 1268.591132284079
                },
                {
                    "x": 579.0896551724137,
                    "y": 1268.591132284079
                }
            ]
        }
    ],
    "version": "2.1.0"
}