{
    "asset": {
        "format": "jpg",
        "id": "63667ac79073fcb9c01d0ff860c8a25e",
        "name": "cbbf474fd322.jpg",
        "path": "file:F:/ArTaxOr/Diptera/cbbf474fd322.jpg",
        "size": {
            "width": 1600,
            "height": 1201
        },
        "state": 2,
        "type": 1
    },
    "regions": [
        {
            "id": "qE-O_ziQb",
            "type": "RECTANGLE",
            "tags": [
                "Diptera"
            ],
            "boundingBox": {
                "height": 861.6369731800767,
                "width": 767.2178289000718,
                "left": 381.7936736161035,
                "top": 102.38409961685824
            },
            "points": [
                {
                    "x": 381.7936736161035,
                    "y": 102.38409961685824
                },
                {
                    "x": 1149.0115025161754,
                    "y": 102.38409961685824
                },
                {
                    "x": 1149.0115025161754,
                    "y": 964.021072796935
                },
                {
                    "x": 381.7936736161035,
                    "y": 964.021072796935
                }
            ]
        }
    ],
    "version": "2.1.0"
}