{
    "asset": {
        "format": "jpg",
        "id": "68f4fe747e40d8e6c0dd0ceb17ca79e9",
        "name": "cb2a7e2acb48.jpg",
        "path": "file:F:/ArTaxOr/Araneae/cb2a7e2acb48.jpg",
        "size": {
            "width": 1800,
            "height": 1350
        },
        "state": 2,
        "type": 1
    },
    "regions": [
        {
            "id": "CLv40rTlG",
            "type": "RECTANGLE",
            "tags": [
                "Araneae",
                "_truncated"
            ],
            "boundingBox": {
                "height": 1243.9655172413793,
                "width": 1589.2241379310344,
                "left": 191.3793103448276,
                "top": 0
            },
            "points": [
                {
                    "x": 191.3793103448276,
                    "y": 0
                },
                {
                    "x": 1780.603448275862,
                    "y": 0
                },
                {
                    "x": 1780.603448275862,
                    "y": 1243.9655172413793
                },
                {
                    "x": 191.3793103448276,
                    "y": 1243.9655172413793
                }
            ]
        }
    ],
    "version": "2.1.0"
}