{
    "asset": {
        "format": "jpg",
        "id": "6b83f10b71e130dd061e6bf4a54b1617",
        "name": "ad0861185835.jpg",
        "path": "file:F:/ArTaxOr/Lepidoptera/ad0861185835.jpg",
        "size": {
            "width": 1870,
            "height": 1553
        },
        "state": 2,
        "type": 1
    },
    "regions": [
        {
            "id": "7H98hICN2",
            "type": "RECTANGLE",
            "tags": [
                "Lepidoptera"
            ],
            "boundingBox": {
                "height": 1408.7078544061303,
                "width": 1130.6284805091489,
                "left": 345.23219968178205,
                "top": 144.29214559386972
            },
            "points": [
                {
                    "x": 345.23219968178205,
                    "y": 144.29214559386972
                },
                {
                    "x": 1475.860680190931,
                    "y": 144.29214559386972
                },
                {
                    "x": 1475.860680190931,
                    "y": 1553
                },
                {
                    "x": 345.23219968178205,
                    "y": 1553
                }
            ]
        }
    ],
    "version": "2.1.0"
}