{
    "asset": {
        "format": "jpg",
        "id": "6cdd44f274a378c066d7c560c2d33d8a",
        "name": "68c0c1ff321e.jpg",
        "path": "file:F:/ArTaxOr/Odonata/68c0c1ff321e.jpg",
        "size": {
            "width": 2048,
            "height": 1536
        },
        "state": 2,
        "type": 1
    },
    "regions": [
        {
            "id": "pv49crEZq",
            "type": "RECTANGLE",
            "tags": [
                "Odonata"
            ],
            "boundingBox": {
                "height": 1106.5420560747664,
                "width": 1239.3271028037382,
                "left": 450.9906542056074,
                "top": 301.4579439252336
            },
            "points": [
                {
                    "x": 450.9906542056074,
                    "y": 301.4579439252336
                },
                {
                    "x": 1690.3177570093458,
                    "y": 301.4579439252336
                },
                {
                    "x": 1690.3177570093458,
                    "y": 1408
                },
                {
                    "x": 450.9906542056074,
                    "y": 1408
                }
            ]
        }
    ],
    "version": "2.1.0"
}