{
    "asset": {
        "format": "jpg",
        "id": "7067fd6a59bbcc922c6b7567e5e588ce",
        "name": "ed990e7f971b.jpg",
        "path": "file:F:/ArTaxOr/Diptera/ed990e7f971b.jpg",
        "size": {
            "width": 1068,
            "height": 712
        },
        "state": 2,
        "type": 1
    },
    "regions": [
        {
            "id": "adnn6Btee",
            "type": "RECTANGLE",
            "tags": [
                "Hymenoptera"
            ],
            "boundingBox": {
                "height": 381.40227507755947,
                "width": 398.93590627153685,
                "left": 341.5244658855961,
                "top": 212.548474663909
            },
            "points": [
                {
                    "x": 341.5244658855961,
                    "y": 212.548474663909
                },
                {
                    "x": 740.460372157133,
                    "y": 212.548474663909
                },
                {
                    "x": 740.460372157133,
                    "y": 593.9507497414685
                },
                {
                    "x": 341.5244658855961,
                    "y": 593.9507497414685
                }
            ]
        }
    ],
    "version": "2.1.0"
}