{
    "asset": {
        "format": "jpg",
        "id": "797c5df2eca1612558d706ac185b3dc8",
        "name": "8703ba49f13f.jpg",
        "path": "file:F:/ArTaxOr/Hemiptera/8703ba49f13f.jpg",
        "size": {
            "width": 1536,
            "height": 2048
        },
        "state": 2,
        "type": 1
    },
    "regions": [
        {
            "id": "xfHjvveVu",
            "type": "RECTANGLE",
            "tags": [
                "Hemiptera"
            ],
            "boundingBox": {
                "height": 1894.9885057471263,
                "width": 1306.4827586206895,
                "left": 146.14559386973178,
                "top": 21.57854406130268
            },
            "points": [
                {
                    "x": 146.14559386973178,
                    "y": 21.57854406130268
                },
                {
                    "x": 1452.6283524904213,
                    "y": 21.57854406130268
                },
                {
                    "x": 1452.6283524904213,
                    "y": 1916.567049808429
                },
                {
                    "x": 146.14559386973178,
                    "y": 1916.567049808429
                }
            ]
        }
    ],
    "version": "2.1.0"
}