{
    "asset": {
        "format": "jpg",
        "id": "7ff1da8032f6a748e57b35501ea1e4c3",
        "name": "50cb80d182f7.jpg",
        "path": "file:F:/ArTaxOr/Hemiptera/50cb80d182f7.jpg",
        "size": {
            "width": 2048,
            "height": 1378
        },
        "state": 2,
        "type": 1
    },
    "regions": [
        {
            "id": "e_a45CtI3",
            "type": "RECTANGLE",
            "tags": [
                "Hemiptera"
            ],
            "boundingBox": {
                "height": 1319.8700371413934,
                "width": 1631.3379310344826,
                "left": 165.25241379310344,
                "top": 0
            },
            "points": [
                {
                    "x": 165.25241379310344,
                    "y": 0
                },
                {
                    "x": 1796.590344827586,
                    "y": 0
                },
                {
                    "x": 1796.590344827586,
                    "y": 1319.8700371413934
                },
                {
                    "x": 165.25241379310344,
                    "y": 1319.8700371413934
                }
            ]
        }
    ],
    "version": "2.1.0"
}