{
    "asset": {
        "format": "jpg",
        "id": "8396e339ab90f139c2127c084b7c9a53",
        "name": "e2cb42152edb.jpg",
        "path": "file:F:/ArTaxOr/Hymenoptera/e2cb42152edb.jpg",
        "size": {
            "width": 1920,
            "height": 1280
        },
        "state": 2,
        "type": 1
    },
    "regions": [
        {
            "id": "slaA1KGyl",
            "type": "RECTANGLE",
            "tags": [
                "Hymenoptera",
                "_blurred"
            ],
            "boundingBox": {
                "height": 292.53360910031023,
                "width": 314.9276361130255,
                "left": 832.3087525844246,
                "top": 44.570837642192345
            },
            "points": [
                {
                    "x": 832.3087525844246,
                    "y": 44.570837642192345
                },
                {
                    "x": 1147.2363886974501,
                    "y": 44.570837642192345
                },
                {
                    "x": 1147.2363886974501,
                    "y": 337.1044467425026
                },
                {
                    "x": 832.3087525844246,
                    "y": 337.1044467425026
                }
            ]
        },
        {
            "id": "yYqPhraQA",
            "type": "RECTANGLE",
            "tags": [
                "Hymenoptera"
            ],
            "boundingBox": {
                "height": 259.44157187176836,
                "width": 255.38249483115095,
                "left": 853.4803583735355,
                "top": 551.540847983454
            },
            "points": [
                {
                    "x": 853.4803583735355,
                    "y": 551.540847983454
                },
                {
                    "x": 1108.8628532046864,
                    "y": 551.540847983454
                },
                {
                    "x": 1108.8628532046864,
                    "y": 810.9824198552224
                },
                {
                    "x": 853.4803583735355,
                    "y": 810.9824198552224
                }
            ]
        }
    ],
    "version": "2.1.0"
}