{
    "asset": {
        "format": "jpg",
        "id": "86a516161fe285af9420842f50e6c226",
        "name": "471c1c8fab4b.jpg",
        "path": "file:F:/ArTaxOr/Coleoptera/471c1c8fab4b.jpg",
        "size": {
            "width": 2048,
            "height": 1365
        },
        "state": 2,
        "type": 1
    },
    "regions": [
        {
            "id": "diklm9366",
            "type": "RECTANGLE",
            "tags": [
                "Coleoptera"
            ],
            "boundingBox": {
                "height": 105.86866597724924,
                "width": 139.73259820813232,
                "left": 1024.7057201929704,
                "top": 321.22317735263704
            },
            "points": [
                {
                    "x": 1024.7057201929704,
                    "y": 321.22317735263704
                },
                {
                    "x": 1164.4383184011026,
                    "y": 321.22317735263704
                },
                {
                    "x": 1164.4383184011026,
                    "y": 427.0918433298863
                },
                {
                    "x": 1024.7057201929704,
                    "y": 427.0918433298863
                }
            ]
        }
    ],
    "version": "2.1.0"
}