{
    "asset": {
        "format": "jpg",
        "id": "888775a06765776e9d23e5a81492e00d",
        "name": "6ee9a01b8c1d.jpg",
        "path": "file:F:/ArTaxOr/Araneae/6ee9a01b8c1d.jpg",
        "size": {
            "width": 1400,
            "height": 933
        },
        "state": 2,
        "type": 1
    },
    "regions": [
        {
            "id": "wIUg1H6Qu",
            "type": "RECTANGLE",
            "tags": [
                "Araneae"
            ],
            "boundingBox": {
                "height": 302.3074534161491,
                "width": 726.0689655172414,
                "left": 374.62068965517244,
                "top": 321.79022709627327
            },
            "points": [
                {
                    "x": 374.62068965517244,
                    "y": 321.79022709627327
                },
                {
                    "x": 1100.689655172414,
                    "y": 321.79022709627327
                },
                {
                    "x": 1100.689655172414,
                    "y": 624.0976805124224
                },
                {
                    "x": 374.62068965517244,
                    "y": 624.0976805124224
                }
            ]
        }
    ],
    "version": "2.1.0"
}