{
    "asset": {
        "format": "jpg",
        "id": "a31b23e4602583905b8f1ba56dcb97d5",
        "name": "df49c8bf30c6.jpg",
        "path": "file:F:/ArTaxOr/Araneae/df49c8bf30c6.jpg",
        "size": {
            "width": 1600,
            "height": 1065
        },
        "state": 2,
        "type": 1
    },
    "regions": [
        {
            "id": "7YT4LP_xL",
            "type": "RECTANGLE",
            "tags": [
                "Araneae"
            ],
            "boundingBox": {
                "height": 570.5751295336787,
                "width": 602.4827586206897,
                "left": 342.0689655172414,
                "top": 182.73647992227978
            },
            "points": [
                {
                    "x": 342.0689655172414,
                    "y": 182.73647992227978
                },
                {
                    "x": 944.551724137931,
                    "y": 182.73647992227978
                },
                {
                    "x": 944.551724137931,
                    "y": 753.3116094559585
                },
                {
                    "x": 342.0689655172414,
                    "y": 753.3116094559585
                }
            ]
        }
    ],
    "version": "2.1.0"
}