{
    "asset": {
        "format": "jpg",
        "id": "a49895a9b227b839a5d9228a670f7bed",
        "name": "45b6734e8287.jpg",
        "path": "file:F:/ArTaxOr/Hymenoptera/45b6734e8287.jpg",
        "size": {
            "width": 3470,
            "height": 2550
        },
        "state": 2,
        "type": 1
    },
    "regions": [
        {
            "id": "v60aJ7e-g",
            "type": "RECTANGLE",
            "tags": [
                "Hymenoptera"
            ],
            "boundingBox": {
                "height": 566.6666666666666,
                "width": 593.3919774806475,
                "left": 798.1335767065447,
                "top": 727.8735632183908
            },
            "points": [
                {
                    "x": 798.1335767065447,
                    "y": 727.8735632183908
                },
                {
                    "x": 1391.525554187192,
                    "y": 727.8735632183908
                },
                {
                    "x": 1391.525554187192,
                    "y": 1294.5402298850574
                },
                {
                    "x": 798.1335767065447,
                    "y": 1294.5402298850574
                }
            ]
        }
    ],
    "version": "2.1.0"
}