{
    "asset": {
        "format": "jpg",
        "id": "a5ed87b134793645ee3defaa3867cb68",
        "name": "23c47ae0d481.jpg",
        "path": "file:F:/ArTaxOr/Coleoptera/23c47ae0d481.jpg",
        "size": {
            "width": 2048,
            "height": 1361
        },
        "state": 2,
        "type": 1
    },
    "regions": [
        {
            "id": "fwlopG8OQ",
            "type": "RECTANGLE",
            "tags": [
                "Coleoptera"
            ],
            "boundingBox": {
                "height": 502.6099585062241,
                "width": 468.59820813232255,
                "left": 985.1853893866299,
                "top": 587.5180400674275
            },
            "points": [
                {
                    "x": 985.1853893866299,
                    "y": 587.5180400674275
                },
                {
                    "x": 1453.7835975189523,
                    "y": 587.5180400674275
                },
                {
                    "x": 1453.7835975189523,
                    "y": 1090.1279985736514
                },
                {
                    "x": 985.1853893866299,
                    "y": 1090.1279985736514
                }
            ]
        }
    ],
    "version": "2.1.0"
}