{
    "asset": {
        "format": "jpg",
        "id": "a845f5b5568d58837c31bc87e5da8f74",
        "name": "1ca502738e6f.jpg",
        "path": "file:F:/ArTaxOr/Hemiptera/1ca502738e6f.jpg",
        "size": {
            "width": 1920,
            "height": 1280
        },
        "state": 2,
        "type": 1
    },
    "regions": [
        {
            "id": "zV0HweI_R",
            "type": "RECTANGLE",
            "tags": [
                "Hemiptera",
                "_occluded"
            ],
            "boundingBox": {
                "height": 661.8407445708376,
                "width": 734.8965517241379,
                "left": 630.2896551724137,
                "top": 430.6514994829369
            },
            "points": [
                {
                    "x": 630.2896551724137,
                    "y": 430.6514994829369
                },
                {
                    "x": 1365.1862068965518,
                    "y": 430.6514994829369
                },
                {
                    "x": 1365.1862068965518,
                    "y": 1092.4922440537746
                },
                {
                    "x": 630.2896551724137,
                    "y": 1092.4922440537746
                }
            ]
        }
    ],
    "version": "2.1.0"
}