{
    "asset": {
        "format": "jpg",
        "id": "b066f20ba0ec574f5187cf8681ac355b",
        "name": "4376411c04e7.jpg",
        "path": "file:F:/ArTaxOr/Araneae/4376411c04e7.jpg",
        "size": {
            "width": 1087,
            "height": 944
        },
        "state": 2,
        "type": 1
    },
    "regions": [
        {
            "id": "qRdGmah50",
            "type": "RECTANGLE",
            "tags": [
                "Araneae"
            ],
            "boundingBox": {
                "height": 821.9310344827586,
                "width": 892.5698835274542,
                "left": 190.4312993968386,
                "top": 115.73946360153256
            },
            "points": [
                {
                    "x": 190.4312993968386,
                    "y": 115.73946360153256
                },
                {
                    "x": 1083.0011829242928,
                    "y": 115.73946360153256
                },
                {
                    "x": 1083.0011829242928,
                    "y": 937.6704980842911
                },
                {
                    "x": 190.4312993968386,
                    "y": 937.6704980842911
                }
            ]
        }
    ],
    "version": "2.1.0"
}