{
    "asset": {
        "format": "jpg",
        "id": "c9c8f55c1c6b0acb480c4bb4a64b64f8",
        "name": "a4f11804a01e.jpg",
        "path": "file:F:/ArTaxOr/Odonata/a4f11804a01e.jpg",
        "size": {
            "width": 2048,
            "height": 1536
        },
        "state": 2,
        "type": 1
    },
    "regions": [
        {
            "id": "R7Rf_vAiR",
            "type": "RECTANGLE",
            "tags": [
                "Odonata"
            ],
            "boundingBox": {
                "height": 361.27102803738313,
                "width": 1666.392523364486,
                "left": 215.3271028037383,
                "top": 762.018691588785
            },
            "points": [
                {
                    "x": 215.3271028037383,
                    "y": 762.018691588785
                },
                {
                    "x": 1881.719626168224,
                    "y": 762.018691588785
                },
                {
                    "x": 1881.719626168224,
                    "y": 1123.289719626168
                },
                {
                    "x": 215.3271028037383,
                    "y": 1123.289719626168
                }
            ]
        }
    ],
    "version": "2.1.0"
}