{
    "asset": {
        "format": "jpg",
        "id": "cf0f10946e11c56f114e049cacb461b5",
        "name": "785ad017ed10.jpg",
        "path": "file:F:/ArTaxOr/Araneae/785ad017ed10.jpg",
        "size": {
            "width": 1378,
            "height": 2048
        },
        "state": 2,
        "type": 1
    },
    "regions": [
        {
            "id": "vyYwZL0TG",
            "type": "RECTANGLE",
            "tags": [
                "Araneae"
            ],
            "boundingBox": {
                "height": 1445.7624521072796,
                "width": 1008.962962962963,
                "left": 187.92303240740742,
                "top": 325.639846743295
            },
            "points": [
                {
                    "x": 187.92303240740742,
                    "y": 325.639846743295
                },
                {
                    "x": 1196.8859953703704,
                    "y": 325.639846743295
                },
                {
                    "x": 1196.8859953703704,
                    "y": 1771.4022988505747
                },
                {
                    "x": 187.92303240740742,
                    "y": 1771.4022988505747
                }
            ]
        }
    ],
    "version": "2.1.0"
}