{
    "asset": {
        "format": "jpg",
        "id": "d0760bdf1da830a11427dfce18d19583",
        "name": "3696b469068d.jpg",
        "path": "file:F:/ArTaxOr/Hemiptera/3696b469068d.jpg",
        "size": {
            "width": 2848,
            "height": 4272
        },
        "state": 2,
        "type": 1
    },
    "regions": [
        {
            "id": "vzdVOwytZ",
            "type": "RECTANGLE",
            "tags": [
                "Hemiptera"
            ],
            "boundingBox": {
                "height": 1947.7701149425286,
                "width": 2009.1494252873563,
                "left": 646.5287356321838,
                "top": 380.55172413793105
            },
            "points": [
                {
                    "x": 646.5287356321838,
                    "y": 380.55172413793105
                },
                {
                    "x": 2655.67816091954,
                    "y": 380.55172413793105
                },
                {
                    "x": 2655.67816091954,
                    "y": 2328.3218390804595
                },
                {
                    "x": 646.5287356321838,
                    "y": 2328.3218390804595
                }
            ]
        }
    ],
    "version": "2.1.0"
}