{
    "asset": {
        "format": "jpg",
        "id": "d6c72591ce4f2997a155ef6d8fb9afdf",
        "name": "6238cc39e8ce.jpg",
        "path": "file:F:/ArTaxOr/Hemiptera/6238cc39e8ce.jpg",
        "size": {
            "width": 2048,
            "height": 1365
        },
        "state": 2,
        "type": 1
    },
    "regions": [
        {
            "id": "S0pxvO4vo",
            "type": "RECTANGLE",
            "tags": [
                "Hemiptera",
                "_occluded"
            ],
            "boundingBox": {
                "height": 1069.6739130434783,
                "width": 1867.2110344827586,
                "left": 56.49655172413793,
                "top": 46.939538043478265
            },
            "points": [
                {
                    "x": 56.49655172413793,
                    "y": 46.939538043478265
                },
                {
                    "x": 1923.7075862068964,
                    "y": 46.939538043478265
                },
                {
                    "x": 1923.7075862068964,
                    "y": 1116.6134510869565
                },
                {
                    "x": 56.49655172413793,
                    "y": 1116.6134510869565
                }
            ]
        }
    ],
    "version": "2.1.0"
}