{
    "asset": {
        "format": "jpg",
        "id": "d7beba277c92ffbdf188891204de923c",
        "name": "ec12ba48d984.jpg",
        "path": "file:F:/ArTaxOr/Lepidoptera/ec12ba48d984.jpg",
        "size": {
            "width": 3872,
            "height": 2592
        },
        "state": 2,
        "type": 1
    },
    "regions": [
        {
            "id": "933eguCKP",
            "type": "RECTANGLE",
            "tags": [
                "Lepidoptera"
            ],
            "boundingBox": {
                "height": 1663.0442842430484,
                "width": 1339.5892487939352,
                "left": 2244.212267401792,
                "top": 319.4536560247168
            },
            "points": [
                {
                    "x": 2244.212267401792,
                    "y": 319.4536560247168
                },
                {
                    "x": 3583.8015161957273,
                    "y": 319.4536560247168
                },
                {
                    "x": 3583.8015161957273,
                    "y": 1982.497940267765
                },
                {
                    "x": 2244.212267401792,
                    "y": 1982.497940267765
                }
            ]
        },
        {
            "id": "8AiVyl6Qp",
            "type": "RECTANGLE",
            "tags": [
                "Lepidoptera"
            ],
            "boundingBox": {
                "height": 1142.5087538619978,
                "width": 1699.8373535492765,
                "left": 872.6009648518263,
                "top": 941.4268795056643
            },
            "points": [
                {
                    "x": 872.6009648518263,
                    "y": 941.4268795056643
                },
                {
                    "x": 2572.4383184011026,
                    "y": 941.4268795056643
                },
                {
                    "x": 2572.4383184011026,
                    "y": 2083.935633367662
                },
                {
                    "x": 872.6009648518263,
                    "y": 2083.935633367662
                }
            ]
        }
    ],
    "version": "2.1.0"
}