{
    "asset": {
        "format": "jpg",
        "id": "d910c36a3c8671c56bf065d12ee81247",
        "name": "b18048b234c7.jpg",
        "path": "file:F:/ArTaxOr/Coleoptera/b18048b234c7.jpg",
        "size": {
            "width": 2048,
            "height": 1365
        },
        "state": 2,
        "type": 1
    },
    "regions": [
        {
            "id": "0nLT9j8Qb",
            "type": "RECTANGLE",
            "tags": [
                "Coleoptera"
            ],
            "boundingBox": {
                "height": 540.635987590486,
                "width": 595.6278428669883,
                "left": 577.2791178497588,
                "top": 472.26247414684593
            },
            "points": [
                {
                    "x": 577.2791178497588,
                    "y": 472.26247414684593
                },
                {
                    "x": 1172.906960716747,
                    "y": 472.26247414684593
                },
                {
                    "x": 1172.906960716747,
                    "y": 1012.898461737332
                },
                {
                    "x": 577.2791178497588,
                    "y": 1012.898461737332
                }
            ]
        }
    ],
    "version": "2.1.0"
}