{
    "asset": {
        "format": "jpg",
        "id": "da1e38b31fd30ff88d619d5653ba8a40",
        "name": "29c4408fc356.jpg",
        "path": "file:F:/ArTaxOr/Hymenoptera/29c4408fc356.jpg",
        "size": {
            "width": 2000,
            "height": 1334
        },
        "state": 2,
        "type": 1
    },
    "regions": [
        {
            "id": "LgyfCn-AG",
            "type": "RECTANGLE",
            "tags": [
                "Hymenoptera"
            ],
            "boundingBox": {
                "height": 709.7210743801652,
                "width": 639.5589248793935,
                "left": 697.4500344589937,
                "top": 349.92952608471074
            },
            "points": [
                {
                    "x": 697.4500344589937,
                    "y": 349.92952608471074
                },
                {
                    "x": 1337.0089593383873,
                    "y": 349.92952608471074
                },
                {
                    "x": 1337.0089593383873,
                    "y": 1059.6506004648759
                },
                {
                    "x": 697.4500344589937,
                    "y": 1059.6506004648759
                }
            ]
        }
    ],
    "version": "2.1.0"
}