{
    "asset": {
        "format": "jpg",
        "id": "da94a0b3e6060bc44d9a1f83a0c81904",
        "name": "a471aed716a7.jpg",
        "path": "file:F:/ArTaxOr/Coleoptera/a471aed716a7.jpg",
        "size": {
            "width": 1026,
            "height": 693
        },
        "state": 2,
        "type": 1
    },
    "regions": [
        {
            "id": "igwKFYTPS",
            "type": "RECTANGLE",
            "tags": [
                "Coleoptera"
            ],
            "boundingBox": {
                "height": 439.84285714285716,
                "width": 801.1426602343212,
                "left": 158.39007580978637,
                "top": 130.13638392857143
            },
            "points": [
                {
                    "x": 158.39007580978637,
                    "y": 130.13638392857143
                },
                {
                    "x": 959.5327360441075,
                    "y": 130.13638392857143
                },
                {
                    "x": 959.5327360441075,
                    "y": 569.9792410714286
                },
                {
                    "x": 158.39007580978637,
                    "y": 569.9792410714286
                }
            ]
        }
    ],
    "version": "2.1.0"
}