{
    "asset": {
        "format": "jpg",
        "id": "ecd5655b98cff79b2a5f55812eeb5d6d",
        "name": "d9ca221fee1b.jpg",
        "path": "file:F:/ArTaxOr/Coleoptera/d9ca221fee1b.jpg",
        "size": {
            "width": 1253,
            "height": 1340
        },
        "state": 2,
        "type": 1
    },
    "regions": [
        {
            "id": "B5hrkZuX0",
            "type": "RECTANGLE",
            "tags": [
                "Coleoptera",
                "_blurred"
            ],
            "boundingBox": {
                "height": 889.4827586206897,
                "width": 784.4088114754098,
                "left": 183.08355212602459,
                "top": 112.95019157088122
            },
            "points": [
                {
                    "x": 183.08355212602459,
                    "y": 112.95019157088122
                },
                {
                    "x": 967.4923636014344,
                    "y": 112.95019157088122
                },
                {
                    "x": 967.4923636014344,
                    "y": 1002.4329501915709
                },
                {
                    "x": 183.08355212602459,
                    "y": 1002.4329501915709
                }
            ]
        }
    ],
    "version": "2.1.0"
}