{
    "asset": {
        "format": "jpg",
        "id": "f05714c066c62dea25cf12a6c1cbe866",
        "name": "24ecde08f51d.jpg",
        "path": "file:F:/ArTaxOr/Hemiptera/24ecde08f51d.jpg",
        "size": {
            "width": 1603,
            "height": 1817
        },
        "state": 2,
        "type": 1
    },
    "regions": [
        {
            "id": "9j4s79qvC",
            "type": "RECTANGLE",
            "tags": [
                "Hemiptera"
            ],
            "boundingBox": {
                "height": 1202.6312260536397,
                "width": 1204.42562432139,
                "left": 228.93006921824104,
                "top": 335.9013409961686
            },
            "points": [
                {
                    "x": 228.93006921824104,
                    "y": 335.9013409961686
                },
                {
                    "x": 1433.355693539631,
                    "y": 335.9013409961686
                },
                {
                    "x": 1433.355693539631,
                    "y": 1538.5325670498084
                },
                {
                    "x": 228.93006921824104,
                    "y": 1538.5325670498084
                }
            ]
        }
    ],
    "version": "2.1.0"
}